py3nvml/__init__.py
py3nvml/nvidia_smi.py
py3nvml/py3nvml.py
py3nvml/utils.py
py3nvml-0.2.7.data/scripts/py3smi
py3nvml-0.2.7.dist-info/LICENSE
py3nvml-0.2.7.dist-info/METADATA
py3nvml-0.2.7.dist-info/WHEEL
py3nvml-0.2.7.dist-info/top_level.txt
py3nvml-0.2.7.dist-info/RECORD
