Metadata-Version: 1.1
Name: py3nvml
Version: 0.2.7
Summary: Python 3 Bindings for the NVIDIA Management Library
Home-page: https://github.com/fbcotter/py3nvml.git
Author: Fergal Cotter
Author-email: fbc23@cam.ac.uk
License: BSD
Download-URL: https://github.com/fbcotter/py3nvml/archive/0.2.7.tar.gz
Platform: UNKNOWN
Classifier: Programming Language :: Python :: 3.5
Classifier: Development Status :: 3 - Alpha
Classifier: Intended Audience :: Developers
Classifier: Intended Audience :: System Administrators
Classifier: License :: OSI Approved :: BSD License
Classifier: Operating System :: Microsoft :: Windows
Classifier: Operating System :: POSIX :: Linux
Classifier: Programming Language :: Python
Classifier: Topic :: Software Development :: Libraries :: Python Modules
Classifier: Topic :: System :: Hardware
Classifier: Topic :: System :: Systems Administration
